{
    "school_name": "",
    "locations": [
        {
            "city": "dublin",
            "country": "ireland",
            "address": "Not specified",
            "courses": [
                {
                    "name": "Standard General English",
                    "lessons_per_week": 20,
                    "description": "General English for improving communication skills",
                    "prices": [
                        {
                            "duration": "2-4 weeks",
                            "price": "355",
                            "currency": "EUR"
                        },
                        {
                            "duration": "5-11 weeks",
                            "price": "\u20ac315",
                            "currency": "EUR"
                        },
                        {
                            "duration": "12-23 weeks",
                            "price": "\u20ac285",
                            "currency": "EUR"
                        },
                        {
                            "duration": "24-35 weeks",
                            "price": "\u20ac265",
                            "currency": "EUR"
                        },
                        {
                            "duration": "36+ weeks",
                            "price": "\u20ac255",
                            "currency": "EUR"
                        }
                    ],
                    "requirements": null
                },
                {
                    "name": "Intensive General English",
                    "lessons_per_week": 26,
                    "description": "Morning and afternoon classes Mon-Fri",
                    "prices": [
                        {
                            "duration": "2-4 weeks",
                            "price": "\u20ac425",
                            "currency": "EUR"
                        },
                        {
                            "duration": "5-11 weeks",
                            "price": "\u20ac400",
                            "currency": "EUR"
                        },
                        {
                            "duration": "12-23 weeks",
                            "price": "\u20ac385",
                            "currency": "EUR"
                        },
                        {
                            "duration": "24-35 weeks",
                            "price": "\u20ac345",
                            "currency": "EUR"
                        },
                        {
                            "duration": "36+ weeks",
                            "price": "\u20ac330",
                            "currency": "EUR"
                        }
                    ],
                    "requirements": null
                }
            ],
            "accommodations": [
                {
                    "type": "Homestay",
                    "price_per_week": "280",
                    "description": "Includes single room and meals (breakfast and dinner).",
                    "supplements": {
                        "summer": "35/week",
                        "summer_supplement": "\u20ac35 per week",
                        "Single Room Summer Supplement": "\u20ac35/week from June 1st to September 1st",
                        "Special Diet Supplement": "\u20ac35/week",
                        "Christmas Supplement": "\u20ac345 for December 20, 2025 to January 3, 2026"
                    }
                },
                {
                    "type": "Residential - Auburn and Crestfield",
                    "price_per_week": "From \u20ac300 (Single), \u20ac265 (Shared)",
                    "description": "Self-catering, private residences, 5km to city.",
                    "supplements": null
                },
                {
                    "type": "Residential - Heyday",
                    "price_per_week": "\u20ac399",
                    "description": "Self-catering, individual room within walking distance.",
                    "supplements": null
                },
                {
                    "type": "Self-catering",
                    "price_per_week": "Varies",
                    "description": "Self-service accommodations.",
                    "supplements": null
                }
            ],
            "additional_fees": {
                "registration": "Varies",
                "registration_fee": "\u20ac85",
                "Airport Transfer": "\u20ac85 for one-way"
            }
        },
        {
            "city": "dublin",
            "country": "ireland",
            "address": "Not specified",
            "courses": [
                {
                    "name": "Standard General English",
                    "lessons_per_week": 20,
                    "description": "General English for improving communication skills",
                    "prices": [
                        {
                            "duration": "2-4 weeks",
                            "price": "355",
                            "currency": "EUR"
                        },
                        {
                            "duration": "5-11 weeks",
                            "price": "\u20ac315",
                            "currency": "EUR"
                        },
                        {
                            "duration": "12-23 weeks",
                            "price": "\u20ac285",
                            "currency": "EUR"
                        },
                        {
                            "duration": "24-35 weeks",
                            "price": "\u20ac265",
                            "currency": "EUR"
                        },
                        {
                            "duration": "36+ weeks",
                            "price": "\u20ac255",
                            "currency": "EUR"
                        }
                    ],
                    "requirements": null
                },
                {
                    "name": "Intensive General English",
                    "lessons_per_week": 26,
                    "description": "Morning and afternoon classes Mon-Fri",
                    "prices": [
                        {
                            "duration": "2-4 weeks",
                            "price": "\u20ac425",
                            "currency": "EUR"
                        },
                        {
                            "duration": "5-11 weeks",
                            "price": "\u20ac400",
                            "currency": "EUR"
                        },
                        {
                            "duration": "12-23 weeks",
                            "price": "\u20ac385",
                            "currency": "EUR"
                        },
                        {
                            "duration": "24-35 weeks",
                            "price": "\u20ac345",
                            "currency": "EUR"
                        },
                        {
                            "duration": "36+ weeks",
                            "price": "\u20ac330",
                            "currency": "EUR"
                        }
                    ],
                    "requirements": null
                }
            ],
            "accommodations": [
                {
                    "type": "Homestay",
                    "price_per_week": "280",
                    "description": "Includes single room and meals (breakfast and dinner).",
                    "supplements": {
                        "summer": "35/week",
                        "summer_supplement": "\u20ac35 per week",
                        "Single Room Summer Supplement": "\u20ac35/week from June 1st to September 1st",
                        "Special Diet Supplement": "\u20ac35/week",
                        "Christmas Supplement": "\u20ac345 for December 20, 2025 to January 3, 2026"
                    }
                },
                {
                    "type": "Residential - Auburn and Crestfield",
                    "price_per_week": "From \u20ac300 (Single), \u20ac265 (Shared)",
                    "description": "Self-catering, private residences, 5km to city.",
                    "supplements": null
                },
                {
                    "type": "Residential - Heyday",
                    "price_per_week": "\u20ac399",
                    "description": "Self-catering, individual room within walking distance.",
                    "supplements": null
                },
                {
                    "type": "Self-catering",
                    "price_per_week": "Varies",
                    "description": "Self-service accommodations.",
                    "supplements": null
                }
            ],
            "additional_fees": {
                "registration": "Varies",
                "registration_fee": "\u20ac85",
                "Airport Transfer": "\u20ac85 for one-way"
            }
        },
        {
            "city": "cork",
            "country": "ireland",
            "address": ".",
            "courses": [
                {
                    "name": "Standard General English",
                    "lessons_per_week": 20,
                    "description": "20 lessons per week, 09:00 - 13:00 Monday to Friday",
                    "prices": [
                        {
                            "duration": "2-4 weeks",
                            "price": "\u20ac285",
                            "currency": "EUR"
                        },
                        {
                            "duration": "5-11 weeks",
                            "price": "\u20ac250",
                            "currency": "EUR"
                        },
                        {
                            "duration": "12-23 weeks",
                            "price": "\u20ac225",
                            "currency": "EUR"
                        }
                    ],
                    "requirements": "Available all year"
                }
            ],
            "accommodations": [
                {
                    "type": "Homestay",
                    "price_per_week": "\u20ac200",
                    "description": "Single room with meal plans included",
                    "supplements": {
                        "summer_fee": "\u20ac20 per week",
                        "Christmas Holidays": "\u20ac345/week from 20 Dec to 03 Jan",
                        "Single Room Summer": "\u20ac50/week from May 17 to September 28",
                        "Special Diet": "\u20ac35/week for various diets such as gluten-free or vegetarian"
                    }
                },
                {
                    "type": "Residential",
                    "price_per_week": "\u20ac285",
                    "description": "Accommodation at University College Cork.",
                    "supplements": null
                },
                {
                    "type": "Airport pickup",
                    "price_per_week": "\u20ac60",
                    "description": "One-way transfer to homestay or residence.",
                    "supplements": null
                }
            ],
            "additional_fees": {
                "registration_fee": "\u20ac85 for all students",
                "Accommodation Placement Fee": "\u20ac85"
            }
        },
        {
            "city": "cork",
            "country": "ireland",
            "address": ".",
            "courses": [
                {
                    "name": "Standard General English",
                    "lessons_per_week": 20,
                    "description": "20 lessons per week, 09:00 - 13:00 Monday to Friday",
                    "prices": [
                        {
                            "duration": "2-4 weeks",
                            "price": "\u20ac285",
                            "currency": "EUR"
                        },
                        {
                            "duration": "5-11 weeks",
                            "price": "\u20ac250",
                            "currency": "EUR"
                        },
                        {
                            "duration": "12-23 weeks",
                            "price": "\u20ac225",
                            "currency": "EUR"
                        }
                    ],
                    "requirements": "Available all year"
                }
            ],
            "accommodations": [
                {
                    "type": "Homestay",
                    "price_per_week": "\u20ac200",
                    "description": "Single room with meal plans included",
                    "supplements": {
                        "summer_fee": "\u20ac20 per week",
                        "Christmas Holidays": "\u20ac345/week from 20 Dec to 03 Jan",
                        "Single Room Summer": "\u20ac50/week from May 17 to September 28",
                        "Special Diet": "\u20ac35/week for various diets such as gluten-free or vegetarian"
                    }
                },
                {
                    "type": "Residential",
                    "price_per_week": "\u20ac285",
                    "description": "Accommodation at University College Cork.",
                    "supplements": null
                },
                {
                    "type": "Airport pickup",
                    "price_per_week": "\u20ac60",
                    "description": "One-way transfer to homestay or residence.",
                    "supplements": null
                }
            ],
            "additional_fees": {
                "registration_fee": "\u20ac85 for all students",
                "Accommodation Placement Fee": "\u20ac85"
            }
        },
        {
            "city": "toronto",
            "country": "canada",
            "address": "Unknown",
            "courses": [
                {
                    "name": "Standard General English",
                    "lessons_per_week": 20,
                    "description": "Morning classes Monday to Friday, 09:00 to 12:15.",
                    "prices": [
                        {
                            "duration": "2-4 weeks",
                            "price": "$440",
                            "currency": "CAD"
                        },
                        {
                            "duration": "5-11 weeks",
                            "price": "$415",
                            "currency": "CAD"
                        },
                        {
                            "duration": "12-23 weeks",
                            "price": "$395",
                            "currency": "CAD"
                        },
                        {
                            "duration": "24-35 weeks",
                            "price": "$365",
                            "currency": "CAD"
                        },
                        {
                            "duration": "36+ weeks",
                            "price": "$345",
                            "currency": "CAD"
                        }
                    ],
                    "requirements": null
                }
            ],
            "accommodations": [
                {
                    "type": "Homestay",
                    "price_per_week": "350",
                    "description": "Full-Board Accommodation (Single)",
                    "supplements": {
                        "summer_additional_cost": "30 per week 01 June - 31 Aug"
                    }
                },
                {
                    "type": "Residence",
                    "price_per_week": "525",
                    "description": "Casa Canada (18+ Shared Room, Weekly with Tax)",
                    "supplements": {
                        "monthly_discount": "Minimum 4 weeks"
                    }
                }
            ],
            "additional_fees": {
                "registration_fee": "$195",
                "accommodation_placement_fee": "275",
                "medical_insurance": "3 per day"
            }
        },
        {
            "city": "toronto",
            "country": "canada",
            "address": "Unknown",
            "courses": [
                {
                    "name": "Standard General English",
                    "lessons_per_week": 20,
                    "description": "Morning classes Monday to Friday, 09:00 to 12:15.",
                    "prices": [
                        {
                            "duration": "2-4 weeks",
                            "price": "$440",
                            "currency": "CAD"
                        },
                        {
                            "duration": "5-11 weeks",
                            "price": "$415",
                            "currency": "CAD"
                        },
                        {
                            "duration": "12-23 weeks",
                            "price": "$395",
                            "currency": "CAD"
                        },
                        {
                            "duration": "24-35 weeks",
                            "price": "$365",
                            "currency": "CAD"
                        },
                        {
                            "duration": "36+ weeks",
                            "price": "$345",
                            "currency": "CAD"
                        }
                    ],
                    "requirements": null
                }
            ],
            "accommodations": [
                {
                    "type": "Homestay",
                    "price_per_week": "350",
                    "description": "Full-Board Accommodation (Single)",
                    "supplements": {
                        "summer_additional_cost": "30 per week 01 June - 31 Aug"
                    }
                },
                {
                    "type": "Residence",
                    "price_per_week": "525",
                    "description": "Casa Canada (18+ Shared Room, Weekly with Tax)",
                    "supplements": {
                        "monthly_discount": "Minimum 4 weeks"
                    }
                }
            ],
            "additional_fees": {
                "registration_fee": "$195",
                "accommodation_placement_fee": "275",
                "medical_insurance": "3 per day"
            }
        },
        {
            "city": "vancouver",
            "country": "canada",
            "address": null,
            "courses": [
                {
                    "name": "Standard General English",
                    "lessons_per_week": 20,
                    "description": "09:00 to 12:15 Mon-Fri",
                    "prices": [
                        {
                            "duration": "2-4 weeks",
                            "price": "$440",
                            "currency": "USD"
                        },
                        {
                            "duration": "5-11 weeks",
                            "price": "$415",
                            "currency": "USD"
                        },
                        {
                            "duration": "12-23 weeks",
                            "price": "$395",
                            "currency": "USD"
                        },
                        {
                            "duration": "24 weeks",
                            "price": "$365",
                            "currency": "USD"
                        }
                    ],
                    "requirements": null
                },
                {
                    "name": "Intensive General English",
                    "lessons_per_week": 25,
                    "description": "09:00 to 14:00 Mon-Thu, 09:00 to 12:15 Fridays",
                    "prices": [
                        {
                            "duration": "2-4 weeks",
                            "price": "$465",
                            "currency": "USD"
                        },
                        {
                            "duration": "5-11 weeks",
                            "price": "$445",
                            "currency": "USD"
                        },
                        {
                            "duration": "12-23 weeks",
                            "price": "$420",
                            "currency": "USD"
                        },
                        {
                            "duration": "24 weeks",
                            "price": "$400",
                            "currency": "USD"
                        }
                    ],
                    "requirements": null
                }
            ],
            "accommodations": [
                {
                    "type": "Homestay",
                    "price_per_week": "$375",
                    "description": "Full board single room, additional cost during summer.",
                    "supplements": {
                        "Special Diet": "$45 p/w",
                        "Extra Night": "$60"
                    }
                },
                {
                    "type": "Residence",
                    "price_per_week": "$600",
                    "description": "Economy Downtown.",
                    "supplements": {
                        "Monthly Rate": "$2400"
                    }
                }
            ],
            "additional_fees": {
                "registration": "$195",
                "Accommodation Placement Fee": "$275"
            }
        },
        {
            "city": "vancouver",
            "country": "canada",
            "address": null,
            "courses": [
                {
                    "name": "Standard General English",
                    "lessons_per_week": 20,
                    "description": "09:00 to 12:15 Mon-Fri",
                    "prices": [
                        {
                            "duration": "2-4 weeks",
                            "price": "$440",
                            "currency": "USD"
                        },
                        {
                            "duration": "5-11 weeks",
                            "price": "$415",
                            "currency": "USD"
                        },
                        {
                            "duration": "12-23 weeks",
                            "price": "$395",
                            "currency": "USD"
                        },
                        {
                            "duration": "24 weeks",
                            "price": "$365",
                            "currency": "USD"
                        }
                    ],
                    "requirements": null
                },
                {
                    "name": "Intensive General English",
                    "lessons_per_week": 25,
                    "description": "09:00 to 14:00 Mon-Thu, 09:00 to 12:15 Fridays",
                    "prices": [
                        {
                            "duration": "2-4 weeks",
                            "price": "$465",
                            "currency": "USD"
                        },
                        {
                            "duration": "5-11 weeks",
                            "price": "$445",
                            "currency": "USD"
                        },
                        {
                            "duration": "12-23 weeks",
                            "price": "$420",
                            "currency": "USD"
                        },
                        {
                            "duration": "24 weeks",
                            "price": "$400",
                            "currency": "USD"
                        }
                    ],
                    "requirements": null
                }
            ],
            "accommodations": [
                {
                    "type": "Homestay",
                    "price_per_week": "$375",
                    "description": "Full board single room, additional cost during summer.",
                    "supplements": {
                        "Special Diet": "$45 p/w",
                        "Extra Night": "$60"
                    }
                },
                {
                    "type": "Residence",
                    "price_per_week": "$600",
                    "description": "Economy Downtown.",
                    "supplements": {
                        "Monthly Rate": "$2400"
                    }
                }
            ],
            "additional_fees": {
                "registration": "$195",
                "Accommodation Placement Fee": "$275"
            }
        },
        {
            "city": "london",
            "country": "england",
            "address": null,
            "courses": [
                {
                    "name": "Standard General English",
                    "lessons_per_week": 20,
                    "description": "Morning classes Mon-Fri 9:30-13:00",
                    "prices": [
                        {
                            "duration": "2-4 weeks",
                            "price": "\u00a3275",
                            "currency": "GBP"
                        },
                        {
                            "duration": "5-11 weeks",
                            "price": "\u00a3265",
                            "currency": "GBP"
                        },
                        {
                            "duration": "12+ weeks",
                            "price": "\u00a3255",
                            "currency": "GBP"
                        }
                    ],
                    "requirements": null
                },
                {
                    "name": "Intensive General English",
                    "lessons_per_week": 30,
                    "description": "Morning and afternoon classes, Mon-Fri",
                    "prices": [
                        {
                            "duration": "2-4 weeks",
                            "price": "\u00a3390",
                            "currency": "GBP"
                        },
                        {
                            "duration": "5-11 weeks",
                            "price": "\u00a3370",
                            "currency": "GBP"
                        },
                        {
                            "duration": "12+ weeks",
                            "price": "\u00a3365",
                            "currency": "GBP"
                        }
                    ],
                    "requirements": null
                }
            ],
            "accommodations": [],
            "additional_fees": {
                "registration": "\u00a375"
            }
        },
        {
            "city": "london",
            "country": "england",
            "address": null,
            "courses": [
                {
                    "name": "Standard General English",
                    "lessons_per_week": 20,
                    "description": "Morning classes Mon-Fri 9:30-13:00",
                    "prices": [
                        {
                            "duration": "2-4 weeks",
                            "price": "\u00a3275",
                            "currency": "GBP"
                        },
                        {
                            "duration": "5-11 weeks",
                            "price": "\u00a3265",
                            "currency": "GBP"
                        },
                        {
                            "duration": "12+ weeks",
                            "price": "\u00a3255",
                            "currency": "GBP"
                        }
                    ],
                    "requirements": null
                },
                {
                    "name": "Intensive General English",
                    "lessons_per_week": 30,
                    "description": "Morning and afternoon classes, Mon-Fri",
                    "prices": [
                        {
                            "duration": "2-4 weeks",
                            "price": "\u00a3390",
                            "currency": "GBP"
                        },
                        {
                            "duration": "5-11 weeks",
                            "price": "\u00a3370",
                            "currency": "GBP"
                        },
                        {
                            "duration": "12+ weeks",
                            "price": "\u00a3365",
                            "currency": "GBP"
                        }
                    ],
                    "requirements": null
                }
            ],
            "accommodations": [],
            "additional_fees": {
                "registration": "\u00a375"
            }
        },
        {
            "city": "london",
            "country": "united kingdom",
            "address": null,
            "courses": [],
            "accommodations": [
                {
                    "type": "Homestay (Single)",
                    "price_per_week": "\u00a3280",
                    "description": "Homestay accommodation with half-board.",
                    "supplements": {
                        "Summer Supplement": "\u00a335 per week (July and August)"
                    }
                },
                {
                    "type": "Homestay (Shared)",
                    "price_per_week": "\u00a3235",
                    "description": "Shared Homestay accommodation with half-board.",
                    "supplements": {
                        "Summer Supplement": "\u00a335 per week (July and August)"
                    }
                },
                {
                    "type": "Rathbone Apartments Residential",
                    "price_per_week": "\u00a3275 and up",
                    "description": "Residential accommodation located in Zone 1 in London, available for adults 18+ with a minimum stay of 4 weeks.",
                    "supplements": null
                }
            ],
            "additional_fees": {
                "accommodation placement fee": "\u00a375"
            }
        },
        {
            "city": "london",
            "country": "united kingdom",
            "address": null,
            "courses": [],
            "accommodations": [
                {
                    "type": "Homestay (Single)",
                    "price_per_week": "\u00a3280",
                    "description": "Homestay accommodation with half-board.",
                    "supplements": {
                        "Summer Supplement": "\u00a335 per week (July and August)"
                    }
                },
                {
                    "type": "Homestay (Shared)",
                    "price_per_week": "\u00a3235",
                    "description": "Shared Homestay accommodation with half-board.",
                    "supplements": {
                        "Summer Supplement": "\u00a335 per week (July and August)"
                    }
                },
                {
                    "type": "Rathbone Apartments Residential",
                    "price_per_week": "\u00a3275 and up",
                    "description": "Residential accommodation located in Zone 1 in London, available for adults 18+ with a minimum stay of 4 weeks.",
                    "supplements": null
                }
            ],
            "additional_fees": {
                "accommodation placement fee": "\u00a375"
            }
        },
        {
            "city": "edinburgh",
            "country": "united kingdom",
            "address": null,
            "courses": [],
            "accommodations": [
                {
                    "type": "Homestay (Single)",
                    "price_per_week": "\u00a3280",
                    "description": "Homestay accommodation with half-board.",
                    "supplements": {
                        "Summer Supplement": "\u00a335 per week (July and August)"
                    }
                },
                {
                    "type": "Homestay (Shared)",
                    "price_per_week": "\u00a3235",
                    "description": "Shared Homestay accommodation with half-board.",
                    "supplements": {
                        "Summer Supplement": "\u00a335 per week (July and August)"
                    }
                }
            ],
            "additional_fees": {
                "accommodation placement fee": "\u00a375"
            }
        },
        {
            "city": "edinburgh",
            "country": "united kingdom",
            "address": null,
            "courses": [],
            "accommodations": [
                {
                    "type": "Homestay (Single)",
                    "price_per_week": "\u00a3280",
                    "description": "Homestay accommodation with half-board.",
                    "supplements": {
                        "Summer Supplement": "\u00a335 per week (July and August)"
                    }
                },
                {
                    "type": "Homestay (Shared)",
                    "price_per_week": "\u00a3235",
                    "description": "Shared Homestay accommodation with half-board.",
                    "supplements": {
                        "Summer Supplement": "\u00a335 per week (July and August)"
                    }
                }
            ],
            "additional_fees": {
                "accommodation placement fee": "\u00a375"
            }
        },
        {
            "city": "oxford",
            "country": "uk",
            "address": "N/A",
            "courses": [
                {
                    "name": "Standard General English",
                    "lessons_per_week": 20,
                    "description": "Morning classes Mon-Fri",
                    "prices": [
                        {
                            "duration": "2-4 weeks",
                            "price": "\u00a3275",
                            "currency": "GBP"
                        },
                        {
                            "duration": "5-11 weeks",
                            "price": "\u00a3265",
                            "currency": "GBP"
                        }
                    ],
                    "requirements": null
                },
                {
                    "name": "IELTS Preparation Course",
                    "lessons_per_week": 30,
                    "description": "Morning classes Mon-Fri and afternoons with IELTS focus",
                    "prices": [
                        {
                            "duration": "2-4 weeks",
                            "price": "\u00a3390",
                            "currency": "GBP"
                        }
                    ],
                    "requirements": null
                }
            ],
            "accommodations": [],
            "additional_fees": {
                "registration_fee": "\u00a375"
            }
        },
        {
            "city": "oxford",
            "country": "uk",
            "address": "N/A",
            "courses": [
                {
                    "name": "Standard General English",
                    "lessons_per_week": 20,
                    "description": "Morning classes Mon-Fri",
                    "prices": [
                        {
                            "duration": "2-4 weeks",
                            "price": "\u00a3275",
                            "currency": "GBP"
                        },
                        {
                            "duration": "5-11 weeks",
                            "price": "\u00a3265",
                            "currency": "GBP"
                        }
                    ],
                    "requirements": null
                },
                {
                    "name": "IELTS Preparation Course",
                    "lessons_per_week": 30,
                    "description": "Morning classes Mon-Fri and afternoons with IELTS focus",
                    "prices": [
                        {
                            "duration": "2-4 weeks",
                            "price": "\u00a3390",
                            "currency": "GBP"
                        }
                    ],
                    "requirements": null
                }
            ],
            "accommodations": [],
            "additional_fees": {
                "registration_fee": "\u00a375"
            }
        },
        {
            "city": "oxford",
            "country": "united kingdom",
            "address": "Not specified",
            "courses": [],
            "accommodations": [
                {
                    "type": "Homestay",
                    "price_per_week": "\u00a3280 (Single, Standard)",
                    "description": "Includes half-board accommodation (breakfast and dinner).",
                    "supplements": {
                        "Summer Supplement (July and August)": "\u00a335 per week",
                        "Christmas Holidays Accommodation Fee": "\u00a3350 for the period of 20 Dec to 3 Jan 2026"
                    }
                }
            ],
            "additional_fees": {
                "Airport Transfer from Heathrow Airport": "\u00a3165 (1 passenger), \u00a3170 (2 passengers), \u00a3175 (3 passengers)",
                "Airport Transfer from Gatwick Airport": "\u00a3205 (1 passenger), \u00a3210 (2 passengers), \u00a3215 (3 passengers)",
                "Airport Transfer from Stansted Airport": "\u00a3215 (1 passenger), \u00a3220 (2 passengers), \u00a3225 (3 passengers)"
            }
        },
        {
            "city": "oxford",
            "country": "united kingdom",
            "address": "Not specified",
            "courses": [],
            "accommodations": [
                {
                    "type": "Homestay",
                    "price_per_week": "\u00a3280 (Single, Standard)",
                    "description": "Includes half-board accommodation (breakfast and dinner).",
                    "supplements": {
                        "Summer Supplement (July and August)": "\u00a335 per week",
                        "Christmas Holidays Accommodation Fee": "\u00a3350 for the period of 20 Dec to 3 Jan 2026"
                    }
                }
            ],
            "additional_fees": {
                "Airport Transfer from Heathrow Airport": "\u00a3165 (1 passenger), \u00a3170 (2 passengers), \u00a3175 (3 passengers)",
                "Airport Transfer from Gatwick Airport": "\u00a3205 (1 passenger), \u00a3210 (2 passengers), \u00a3215 (3 passengers)",
                "Airport Transfer from Stansted Airport": "\u00a3215 (1 passenger), \u00a3220 (2 passengers), \u00a3225 (3 passengers)"
            }
        },
        {
            "city": "leeds",
            "country": "united kingdom",
            "address": "6th January - 19th December 2025",
            "courses": [
                {
                    "name": "Standard General English",
                    "lessons_per_week": 20,
                    "description": "09:30-13:00 Mon to Fri",
                    "prices": [
                        {
                            "duration": "2-4 weeks",
                            "price": "\u00a3255",
                            "currency": "GBP"
                        },
                        {
                            "duration": "5-11 weeks",
                            "price": "\u00a3250",
                            "currency": "GBP"
                        },
                        {
                            "duration": "12-23 weeks",
                            "price": "\u00a3240",
                            "currency": "GBP"
                        },
                        {
                            "duration": "24-35 weeks",
                            "price": "\u00a3230",
                            "currency": "GBP"
                        },
                        {
                            "duration": "36+ weeks",
                            "price": "\u00a3225",
                            "currency": "GBP"
                        }
                    ],
                    "requirements": null
                },
                {
                    "name": "Intensive General English",
                    "lessons_per_week": 30,
                    "description": "09:30-13:00 Mon to Fri & 14:00-16:30 Tues to Thurs",
                    "prices": [
                        {
                            "duration": "2-4 weeks",
                            "price": "\u00a3375",
                            "currency": "GBP"
                        },
                        {
                            "duration": "5-11 weeks",
                            "price": "\u00a3360",
                            "currency": "GBP"
                        },
                        {
                            "duration": "12-23 weeks",
                            "price": "\u00a3355",
                            "currency": "GBP"
                        },
                        {
                            "duration": "24-35 weeks",
                            "price": "\u00a3335",
                            "currency": "GBP"
                        },
                        {
                            "duration": "36+ weeks",
                            "price": "\u00a3330",
                            "currency": "GBP"
                        }
                    ],
                    "requirements": null
                }
            ],
            "accommodations": [
                {
                    "type": "Homestay",
                    "price_per_week": "N/A",
                    "description": "Half-board, single room",
                    "supplements": null
                },
                {
                    "type": "Residence",
                    "price_per_week": "\u00a3225",
                    "description": "Year-round, single en-suite room",
                    "supplements": null
                }
            ],
            "additional_fees": {
                "registration_fee": "\u00a375",
                "accommodation_placement": "\u00a375",
                "IELTS_exam": "\u00a3220",
                "digital_ebook": "\u00a332"
            }
        },
        {
            "city": "leeds",
            "country": "united kingdom",
            "address": "6th January - 19th December 2025",
            "courses": [
                {
                    "name": "Standard General English",
                    "lessons_per_week": 20,
                    "description": "09:30-13:00 Mon to Fri",
                    "prices": [
                        {
                            "duration": "2-4 weeks",
                            "price": "\u00a3255",
                            "currency": "GBP"
                        },
                        {
                            "duration": "5-11 weeks",
                            "price": "\u00a3250",
                            "currency": "GBP"
                        },
                        {
                            "duration": "12-23 weeks",
                            "price": "\u00a3240",
                            "currency": "GBP"
                        },
                        {
                            "duration": "24-35 weeks",
                            "price": "\u00a3230",
                            "currency": "GBP"
                        },
                        {
                            "duration": "36+ weeks",
                            "price": "\u00a3225",
                            "currency": "GBP"
                        }
                    ],
                    "requirements": null
                },
                {
                    "name": "Intensive General English",
                    "lessons_per_week": 30,
                    "description": "09:30-13:00 Mon to Fri & 14:00-16:30 Tues to Thurs",
                    "prices": [
                        {
                            "duration": "2-4 weeks",
                            "price": "\u00a3375",
                            "currency": "GBP"
                        },
                        {
                            "duration": "5-11 weeks",
                            "price": "\u00a3360",
                            "currency": "GBP"
                        },
                        {
                            "duration": "12-23 weeks",
                            "price": "\u00a3355",
                            "currency": "GBP"
                        },
                        {
                            "duration": "24-35 weeks",
                            "price": "\u00a3335",
                            "currency": "GBP"
                        },
                        {
                            "duration": "36+ weeks",
                            "price": "\u00a3330",
                            "currency": "GBP"
                        }
                    ],
                    "requirements": null
                }
            ],
            "accommodations": [
                {
                    "type": "Homestay",
                    "price_per_week": "N/A",
                    "description": "Half-board, single room",
                    "supplements": null
                },
                {
                    "type": "Residence",
                    "price_per_week": "\u00a3225",
                    "description": "Year-round, single en-suite room",
                    "supplements": null
                }
            ],
            "additional_fees": {
                "registration_fee": "\u00a375",
                "accommodation_placement": "\u00a375",
                "IELTS_exam": "\u00a3220",
                "digital_ebook": "\u00a332"
            }
        },
        {
            "city": "worthing",
            "country": "united kingdom",
            "address": null,
            "courses": [
                {
                    "name": "Standard General English",
                    "lessons_per_week": 20,
                    "description": "Morning classes Mon-Fri, 9:30 - 13:00",
                    "prices": [
                        {
                            "duration": "2-4 weeks",
                            "price": "\u00a3245",
                            "currency": "GBP"
                        },
                        {
                            "duration": "5-11 weeks",
                            "price": "\u00a3235",
                            "currency": "GBP"
                        },
                        {
                            "duration": "12-23 weeks",
                            "price": "\u00a3225",
                            "currency": "GBP"
                        },
                        {
                            "duration": "24-35 weeks",
                            "price": "\u00a3220",
                            "currency": "GBP"
                        },
                        {
                            "duration": "36+ weeks",
                            "price": "\u00a3210",
                            "currency": "GBP"
                        }
                    ],
                    "requirements": null
                },
                {
                    "name": "Intensive General English",
                    "lessons_per_week": 30,
                    "description": "Morning and afternoon classes Mon-Fri, 9:30 - 13:00 & 14:00 - 16:30",
                    "prices": [
                        {
                            "duration": "2-4 weeks",
                            "price": "\u00a3355",
                            "currency": "GBP"
                        },
                        {
                            "duration": "5-11 weeks",
                            "price": "\u00a3335",
                            "currency": "GBP"
                        }
                    ],
                    "requirements": null
                }
            ],
            "accommodations": [
                {
                    "type": "Homestay (Half-Board)",
                    "price_per_week": "Single room: \u00a3240 p/w, Shared room: \u00a3215 p/w",
                    "description": "Half board with options for summer and special diet supplements.",
                    "supplements": {
                        "summer_supplement": "\u00a335 p/w during July and August",
                        "special_diet_supplement": "\u00a335 p/w",
                        "Christmas_homestay_accommodation": "\u00a3350 p/w (20 Dec to 3 Jan 2026)"
                    }
                }
            ],
            "additional_fees": {
                "accommodation_placement_fee": "\u00a375",
                "airport_transfers_one_way_from_Heathrow": "\u00a3170 (one passenger), \u00a3175 (two passengers), \u00a3180 (three passengers)",
                "airport_transfers_one_way_from_Gatwick": "\u00a3140 (one passenger), \u00a3145 (two passengers), \u00a3150 (three passengers)",
                "airport_transfers_one_way_from_Stansted": "\u00a3250 (one passenger), \u00a3255 (two passengers), \u00a3260 (three passengers)"
            }
        },
        {
            "city": "worthing",
            "country": "united kingdom",
            "address": null,
            "courses": [
                {
                    "name": "Standard General English",
                    "lessons_per_week": 20,
                    "description": "Morning classes Mon-Fri, 9:30 - 13:00",
                    "prices": [
                        {
                            "duration": "2-4 weeks",
                            "price": "\u00a3245",
                            "currency": "GBP"
                        },
                        {
                            "duration": "5-11 weeks",
                            "price": "\u00a3235",
                            "currency": "GBP"
                        },
                        {
                            "duration": "12-23 weeks",
                            "price": "\u00a3225",
                            "currency": "GBP"
                        },
                        {
                            "duration": "24-35 weeks",
                            "price": "\u00a3220",
                            "currency": "GBP"
                        },
                        {
                            "duration": "36+ weeks",
                            "price": "\u00a3210",
                            "currency": "GBP"
                        }
                    ],
                    "requirements": null
                },
                {
                    "name": "Intensive General English",
                    "lessons_per_week": 30,
                    "description": "Morning and afternoon classes Mon-Fri, 9:30 - 13:00 & 14:00 - 16:30",
                    "prices": [
                        {
                            "duration": "2-4 weeks",
                            "price": "\u00a3355",
                            "currency": "GBP"
                        },
                        {
                            "duration": "5-11 weeks",
                            "price": "\u00a3335",
                            "currency": "GBP"
                        }
                    ],
                    "requirements": null
                }
            ],
            "accommodations": [
                {
                    "type": "Homestay (Half-Board)",
                    "price_per_week": "Single room: \u00a3240 p/w, Shared room: \u00a3215 p/w",
                    "description": "Half board with options for summer and special diet supplements.",
                    "supplements": {
                        "summer_supplement": "\u00a335 p/w during July and August",
                        "special_diet_supplement": "\u00a335 p/w",
                        "Christmas_homestay_accommodation": "\u00a3350 p/w (20 Dec to 3 Jan 2026)"
                    }
                }
            ],
            "additional_fees": {
                "accommodation_placement_fee": "\u00a375",
                "airport_transfers_one_way_from_Heathrow": "\u00a3170 (one passenger), \u00a3175 (two passengers), \u00a3180 (three passengers)",
                "airport_transfers_one_way_from_Gatwick": "\u00a3140 (one passenger), \u00a3145 (two passengers), \u00a3150 (three passengers)",
                "airport_transfers_one_way_from_Stansted": "\u00a3250 (one passenger), \u00a3255 (two passengers), \u00a3260 (three passengers)"
            }
        },
        {
            "city": "west sussex",
            "country": "united kingdom",
            "address": "27 South Street, Worthing West Sussex, BN11 3AR",
            "courses": [],
            "accommodations": [],
            "additional_fees": {}
        },
        {
            "city": "west sussex",
            "country": "united kingdom",
            "address": "27 South Street, Worthing West Sussex, BN11 3AR",
            "courses": [],
            "accommodations": [],
            "additional_fees": {}
        }
    ],
    "terms": {
        "cancellation": "Cancellation fees apply for cancellations made 14 days prior to course start.",
        "registration_fees_appliy_to_all": "\u20ac85",
        "lesson_duration": "55 minutes",
        "accommodation": "Accommodation is arranged by request.",
        "insurance": "\u20ac130 per annum for Medi-PEL",
        "payment": "Non-refundable with exceptions during specified periods.",
        "conditions": "All teaching hours are 55 minutes. Maximum class size is 14 students.",
        "tuition_hours": "Standard course: 15 contact hrs/week. Intensive course: 22 contact hrs/week.",
        "examinations": "IELTS: \u20ac215, Cambridge First: \u20ac205, Advanced: \u20ac210",
        "textbook": "Textbook and e-book fee: \u20ac28, IELTS book: \u20ac45",
        "policy_of_care": "Care policy for 16 and 17-year-old students in adult courses.",
        "school_holidays": "No classes on January 01, February 03, March 17, April 18, April 21, May 02, June 04, August 27, October 19, December 25 to January 05, 2026.",
        "teaching_minutes": "45 minutes",
        "maximum_class_size": "16 trainees",
        "accommodation_notice": "Students must arrive at their scheduled time, changes incur extra fees.",
        "medical_insurance": "Strongly advised to take out.",
        "Accommodation Policy": "Half-board, single room guaranteed only for specific periods.",
        "Medical Insurance Policy": "Ensure coverage before leaving home.",
        "Tuition Hour Policy": "Standard Course is 15 hours per week, excluding breaks.",
        "Additional Notes": "Late arrival fees apply.",
        "Medical Insurance": "Not included, needs to be arranged by the student.",
        "Tuition Hours": "45 minutes per teaching hour for courses.",
        "Examinations": "IELTS exam cost is \u00a3220.",
        "Social Activities": "Optional activities available with costs ranging from \u00a38 to \u00a3120, depending on type.",
        "School Holidays": "Specified dates; no refund for these holidays.",
        "other_terms": "Special activities available.",
        "accommodation_terms": "Accommodation in carefully selected homestay, half board.",
        "tuition_hours_notes": "All lessons are 45 minutes each.",
        "exam_fee": "IELTS exam costs: \u20ac220 (subject to change).",
        "additional_materials": "Digital E-Book: \u20ac32.",
        "social_activities": "Organized excursions at an additional cost.",
        "holidays": "01 January, 18\u201321 April, 5 May, 26 May, 25 August, 22 December (2025), 02 January (2026)."
    }
}